calcroad_simulation/__init__.py
calcroad_simulation/functions.py
calcroad_simulation/incident.py
calcroad_simulation/journey.py
calcroad_simulation/pathfinding.py
calcroad_simulation/road.py
calcroad_simulation/settings.py
calcroad_simulation/simulation.py
calcroad_simulation/stream.py
calcroad_simulation/utils.py
calcroad_simulation/vehicule.py
calcroad_simulation/vehicule_v2.py
calcroad_simulation/converter/__init__.py
calcroad_simulation/converter/converter.py
calcroad_simulation/converter/graph.py
calcroad_simulation/converter/models.py
calcroad_simulation/converter/road.py
calcroad_simulation/converter/models/__init__.py
calcroad_simulation/converter/models/functions.py
calcroad_simulation/converter/models/journey.py
calcroad_simulation/converter/models/point.py
calcroad_simulation/converter/models/road.py
calcroad_simulation/converter/models/vehicule.py
old_calcroad_simulation/__init__.py
old_calcroad_simulation/exceptions.py
old_calcroad_simulation/incident.py
old_calcroad_simulation/journey.py
old_calcroad_simulation/pathfinding.py
old_calcroad_simulation/road.py
old_calcroad_simulation/settings.py
old_calcroad_simulation/simulation.py
old_calcroad_simulation/stream.py
old_calcroad_simulation/utils.py
old_calcroad_simulation/vehicule.py
old_calcroad_simulation/vehicule_v2.py
calcroad_simulation-0.1.2.dist-info/METADATA
calcroad_simulation-0.1.2.dist-info/WHEEL
calcroad_simulation-0.1.2.dist-info/top_level.txt
calcroad_simulation-0.1.2.dist-info/RECORD
