Metadata-Version: 2.1
Name: calcroad-simulation
Version: 0.1.2
Summary: CalcROAD simulation
Home-page: https://gitlab.com/urbanize/simulation
Author: Urbanize
Author-email: urbanize.contact@gmail.com
License: UNKNOWN
Platform: UNKNOWN
Classifier: Programming Language :: Python :: 3
Classifier: License :: OSI Approved :: MIT License
Classifier: Operating System :: OS Independent
Requires-Python: >=3.6
Requires-Dist: Dijkstar (==2.5.0)
